{
  "@context": "https://schema.org",
  "@type": "LocalBusiness",
  "name": "Badger Technologies",
  "alternateName": "Badger Tech",
  "description": "Professional IT services, cybersecurity solutions, and technology consulting. Securing tomorrow's technology today.",
  "url": "https://badgertechnologies.us",
  "logo": "https://badgertechnologies.us/images/badger-logo-main.png",
  "image": [
    "https://badgertechnologies.us/images/badger-logo-main.png",
    "https://badgertechnologies.us/images/badger-logo-cybersecurity.png"
  ],
  "telephone": "+1-815-367-6989",
  "email": "info@badgertechnologies.com",
  "address": {
    "@type": "PostalAddress",
    "addressCountry": "US"
  },
  "geo": {
    "@type": "GeoCoordinates"
  },
  "sameAs": [
    "https://github.com/honeybadger2121-home/badgertechnologies-website"
  ],
  "openingHours": [
    "Mo-Fr 08:00-18:00",
    "Sa 09:00-15:00"
  ],
  "priceRange": "$$",
  "serviceArea": {
    "@type": "State",
    "name": "Illinois"
  },
  "hasOfferCatalog": {
    "@type": "OfferCatalog",
    "name": "IT Services",
    "itemListElement": [
      {
        "@type": "Offer",
        "itemOffered": {
          "@type": "Service",
          "name": "Cybersecurity Assessment",
          "description": "Comprehensive security evaluation and threat analysis"
        }
      },
      {
        "@type": "Offer",
        "itemOffered": {
          "@type": "Service",
          "name": "Cloud Solutions",
          "description": "Azure cloud migration and management services"
        }
      },
      {
        "@type": "Offer",
        "itemOffered": {
          "@type": "Service",
          "name": "Network Management",
          "description": "Network design, monitoring, and maintenance"
        }
      },
      {
        "@type": "Offer",
        "itemOffered": {
          "@type": "Service",
          "name": "IT Support",
          "description": "24/7 technical support and system monitoring"
        }
      }
    ]
  },
  "aggregateRating": {
    "@type": "AggregateRating",
    "ratingValue": "5.0",
    "reviewCount": "1"
  },
  "founder": {
    "@type": "Person",
    "name": "Badger Technologies Team"
  }
}
